{
  "_class": "group",
  "booleanOperation": -1,
  "clippingMaskMode": 0,
  "do_objectID": "98C4324F-0A7B-4224-A57F-5ACB21AA8157",
  "exportOptions": {
    "_class": "exportOptions",
    "do_objectID": "4793FE2D-1621-400A-AECD-CF841826F0A0",
    "exportFormats": [
      {
        "_class": "exportFormat",
        "absoluteSize": 0,
        "fileFormat": "png",
        "name": "",
        "namingScheme": 0,
        "scale": 1,
        "visibleScaleType": 0
      }
    ],
    "includedLayerIds": [
    ],
    "layerOptions": 0,
    "shouldTrim": false
  },
  "frame": {
    "_class": "rect",
    "constrainProportions": false,
    "do_objectID": "3F06320C-684A-4B8A-8129-ADE052A94BB8",
    "height": 1024,
    "width": 1101,
    "x": -381,
    "y": 0
  },
  "hasClickThrough": false,
  "hasClippingMask": false,
  "isFixedToViewport": false,
  "isFlippedHorizontal": false,
  "isFlippedVertical": false,
  "isLocked": false,
  "isVisible": true,
  "layerListExpandedType": 2,
  "layers": [
    {
      "class": "rectangle",
      "id": "C49E084E-9B41-4C39-9C59-F1D236D951D6"
    },
    {
      "class": "bitmap",
      "id": "0B376407-2612-4408-B329-B6D4839D93D2"
    }
  ],
  "name": "1.1 Login - Uuario",
  "nameIsFixed": true,
  "resizingConstraint": 63,
  "resizingType": 0,
  "rotation": 0,
  "shouldBreakMaskChain": false,
  "style": {
    "_class": "style",
    "do_objectID": "3638475C-ED87-459C-AD93-B835C912651D",
    "endMarkerType": 0,
    "miterLimit": 10,
    "startMarkerType": 0,
    "windingRule": 1
  }
}