{
  "_class": "shapePath",
  "booleanOperation": -1,
  "clippingMaskMode": 0,
  "do_objectID": "317206F0-998C-4B2C-A35C-8D262FACE753",
  "edited": true,
  "exportOptions": {
    "_class": "exportOptions",
    "do_objectID": "2D3B6A39-2D6D-42C5-99A0-A6C3B82DBBE1",
    "exportFormats": [
    ],
    "includedLayerIds": [
    ],
    "layerOptions": 0,
    "shouldTrim": false
  },
  "frame": {
    "_class": "rect",
    "constrainProportions": false,
    "do_objectID": "13B36F19-0AD3-4E47-8E15-BF501738BF85",
    "height": 52.94727272727305,
    "width": 117.4545454545454,
    "x": 9.272727272727273,
    "y": 9.272727272727272
  },
  "hasClippingMask": false,
  "isClosed": true,
  "isFixedToViewport": false,
  "isFlippedHorizontal": false,
  "isFlippedVertical": false,
  "isLocked": false,
  "isVisible": true,
  "layerListExpandedType": 0,
  "name": "Path",
  "nameIsFixed": false,
  "pointRadiusBehaviour": 0,
  "points": [
    {
      "_class": "curvePoint",
      "cornerRadius": 0,
      "curveFrom": "{1, 0}",
      "curveMode": 1,
      "curveTo": "{1, 0}",
      "hasCurveFrom": false,
      "hasCurveTo": false,
      "point": "{1, 0}"
    },
    {
      "_class": "curvePoint",
      "cornerRadius": 0,
      "curveFrom": "{1, 0.1681260945709335}",
      "curveMode": 1,
      "curveTo": "{1, 0.1681260945709335}",
      "hasCurveFrom": false,
      "hasCurveTo": false,
      "point": "{1, 0.1681260945709335}"
    },
    {
      "_class": "curvePoint",
      "cornerRadius": 0,
      "curveFrom": "{0.4981578947368408, 1}",
      "curveMode": 1,
      "curveTo": "{0.4981578947368408, 1}",
      "hasCurveFrom": false,
      "hasCurveTo": false,
      "point": "{0.4981578947368408, 1}"
    },
    {
      "_class": "curvePoint",
      "cornerRadius": 0,
      "curveFrom": "{0, 0.1681260945709335}",
      "curveMode": 1,
      "curveTo": "{0, 0.1681260945709335}",
      "hasCurveFrom": false,
      "hasCurveTo": false,
      "point": "{0, 0.1681260945709335}"
    },
    {
      "_class": "curvePoint",
      "cornerRadius": 0,
      "curveFrom": "{0, 0}",
      "curveMode": 1,
      "curveTo": "{0, 0}",
      "hasCurveFrom": false,
      "hasCurveTo": false,
      "point": "{0, 0}"
    }
  ],
  "resizingConstraint": 63,
  "resizingType": 0,
  "rotation": 0,
  "shouldBreakMaskChain": false,
  "style": {
    "_class": "style",
    "do_objectID": "859DF3DE-BC9D-438B-99C6-F544D99EF9BB",
    "endMarkerType": 0,
    "fills": [
      {
        "_class": "fill",
        "color": {
          "_class": "color",
          "alpha": 1,
          "blue": 0,
          "green": 0,
          "red": 0
        },
        "fillType": 0,
        "isEnabled": true,
        "noiseIndex": 0,
        "noiseIntensity": 0,
        "patternFillType": 1,
        "patternTileScale": 1
      }
    ],
    "miterLimit": 10,
    "startMarkerType": 0,
    "windingRule": 1
  }
}