{
  "_class": "shapePath",
  "booleanOperation": -1,
  "clippingMaskMode": 0,
  "do_objectID": "0600592F-B0BE-4C14-B2B2-2B964A0D2F3D",
  "edited": true,
  "exportOptions": {
    "_class": "exportOptions",
    "do_objectID": "4B49B103-B5C1-4269-A8A2-AFA861D3B74A",
    "exportFormats": [
    ],
    "includedLayerIds": [
    ],
    "layerOptions": 0,
    "shouldTrim": false
  },
  "frame": {
    "_class": "rect",
    "constrainProportions": false,
    "do_objectID": "FB5F7D1C-93AF-4938-837D-E6D213F53454",
    "height": 65.00000000000003,
    "width": 91.78894900787392,
    "x": 4.249980275859425,
    "y": 10.83333333333335
  },
  "hasClippingMask": false,
  "isClosed": true,
  "isFixedToViewport": false,
  "isFlippedHorizontal": false,
  "isFlippedVertical": false,
  "isLocked": false,
  "isVisible": true,
  "layerListExpandedType": 0,
  "name": "Path",
  "nameIsFixed": false,
  "pointRadiusBehaviour": 1,
  "points": [
    {
      "_class": "curvePoint",
      "cornerRadius": 0,
      "curveFrom": "{0, 1}",
      "curveMode": 1,
      "curveTo": "{0, 1}",
      "hasCurveFrom": false,
      "hasCurveTo": false,
      "point": "{0, 1}"
    },
    {
      "_class": "curvePoint",
      "cornerRadius": 0,
      "curveFrom": "{0, 0.93333333333333335}",
      "curveMode": 1,
      "curveTo": "{0, 0.93333333333333335}",
      "hasCurveFrom": false,
      "hasCurveTo": false,
      "point": "{0, 0.93333333333333335}"
    },
    {
      "_class": "curvePoint",
      "cornerRadius": 0,
      "curveFrom": "{0, 0}",
      "curveMode": 1,
      "curveTo": "{0, 0}",
      "hasCurveFrom": false,
      "hasCurveTo": false,
      "point": "{0, 0}"
    },
    {
      "_class": "curvePoint",
      "cornerRadius": 0,
      "curveFrom": "{1, 0}",
      "curveMode": 1,
      "curveTo": "{1, 0}",
      "hasCurveFrom": false,
      "hasCurveTo": false,
      "point": "{1, 0}"
    },
    {
      "_class": "curvePoint",
      "cornerRadius": 0,
      "curveFrom": "{0.78594744762125246, 0.49313333333333348}",
      "curveMode": 4,
      "curveTo": "{0.79064706563259635, 0.48233333333333328}",
      "hasCurveFrom": true,
      "hasCurveTo": false,
      "point": "{0.79064706563259635, 0.48233333333333328}"
    },
    {
      "_class": "curvePoint",
      "cornerRadius": 0,
      "curveFrom": "{0.79064706563259635, 0.51769999999999994}",
      "curveMode": 4,
      "curveTo": "{0.78594744762125246, 0.50686666666666658}",
      "hasCurveFrom": false,
      "hasCurveTo": true,
      "point": "{0.79064706563259635, 0.51769999999999994}"
    },
    {
      "_class": "curvePoint",
      "cornerRadius": 0,
      "curveFrom": "{1, 1}",
      "curveMode": 1,
      "curveTo": "{1, 1}",
      "hasCurveFrom": false,
      "hasCurveTo": false,
      "point": "{1, 1}"
    }
  ],
  "resizingConstraint": 63,
  "resizingType": 0,
  "rotation": 0,
  "shouldBreakMaskChain": false,
  "style": {
    "_class": "style",
    "do_objectID": "24299319-0012-4040-B5E4-A0CA32E73260",
    "endMarkerType": 0,
    "miterLimit": 10,
    "startMarkerType": 0,
    "windingRule": 1
  }
}