{
  "_class": "group",
  "booleanOperation": -1,
  "clippingMaskMode": 0,
  "do_objectID": "0CAB929A-A5F4-46D8-AD2E-4EFC6C323B64",
  "exportOptions": {
    "_class": "exportOptions",
    "do_objectID": "619249A4-41FA-48DB-AE81-0975DBCBA7D2",
    "exportFormats": [
    ],
    "includedLayerIds": [
    ],
    "layerOptions": 0,
    "shouldTrim": false
  },
  "frame": {
    "_class": "rect",
    "constrainProportions": false,
    "do_objectID": "F8779159-069D-4AC6-9583-DEC94266E60E",
    "height": 48,
    "width": 128,
    "x": 972,
    "y": 834
  },
  "hasClickThrough": false,
  "hasClippingMask": false,
  "isFixedToViewport": false,
  "isFlippedHorizontal": false,
  "isFlippedVertical": false,
  "isLocked": false,
  "isVisible": true,
  "layerListExpandedType": 2,
  "layers": [
    {
      "class": "rectangle",
      "id": "194C02FB-6A61-470E-892A-D2ED0172E8E2"
    },
    {
      "class": "rectangle",
      "id": "771EC28E-CAD9-40D9-B5E2-EFABA2792AE9"
    },
    {
      "class": "symbolInstance",
      "id": "5DEB9721-8F20-4907-9B4A-386A32A411C0"
    },
    {
      "class": "symbolInstance",
      "id": "7EFA837E-679C-49C3-B1F0-2417178EDD55"
    },
    {
      "class": "text",
      "id": "E3A83057-0C84-4482-AF05-E2D4BE4C1CCA"
    }
  ],
  "name": "Group Copy 2",
  "nameIsFixed": false,
  "resizingConstraint": 63,
  "resizingType": 0,
  "rotation": 0,
  "shouldBreakMaskChain": false,
  "style": {
    "_class": "style",
    "do_objectID": "F7408596-06F7-43EE-B7AF-1B94043B938E",
    "endMarkerType": 0,
    "miterLimit": 10,
    "startMarkerType": 0,
    "windingRule": 1
  }
}