{
  "_class": "group",
  "booleanOperation": -1,
  "clippingMaskMode": 0,
  "do_objectID": "18EB3D12-EB00-4110-ADC7-D9BA6CCE2F80",
  "exportOptions": {
    "_class": "exportOptions",
    "do_objectID": "8D7BFA48-8DE5-4FEE-BCE9-7FF903E29BD0",
    "exportFormats": [
    ],
    "includedLayerIds": [
    ],
    "layerOptions": 0,
    "shouldTrim": false
  },
  "frame": {
    "_class": "rect",
    "constrainProportions": false,
    "do_objectID": "AEEC4B17-C067-433D-BE65-F2321197B0AE",
    "height": 38,
    "width": 240,
    "x": 16,
    "y": 0
  },
  "hasClickThrough": false,
  "hasClippingMask": false,
  "isFixedToViewport": false,
  "isFlippedHorizontal": false,
  "isFlippedVertical": false,
  "isLocked": false,
  "isVisible": true,
  "layerListExpandedType": 2,
  "layers": [
    {
      "class": "rectangle",
      "id": "68072A1D-8DC1-4F8F-B805-274B231AB5E8"
    },
    {
      "class": "text",
      "id": "797B33B2-1222-4E4E-86F5-C44756D5403B"
    }
  ],
  "name": "Group 5",
  "nameIsFixed": false,
  "resizingConstraint": 63,
  "resizingType": 0,
  "rotation": 0,
  "shouldBreakMaskChain": false,
  "style": {
    "_class": "style",
    "do_objectID": "B7F8E345-6412-4F55-B0B0-B71F52409D3D",
    "endMarkerType": 0,
    "miterLimit": 10,
    "startMarkerType": 0,
    "windingRule": 1
  }
}