{
  "_class": "text",
  "attributedString": {
    "_class": "attributedString",
    "attributes": [
      {
        "_class": "stringAttribute",
        "attributes": {
          "MSAttributedStringColorAttribute": {
            "_class": "color",
            "alpha": 1,
            "blue": 0.1254901960784314,
            "green": 0.1254901960784314,
            "red": 0.1254901960784314
          },
          "MSAttributedStringFontAttribute": {
            "_class": "fontDescriptor",
            "attributes": {
              "name": "HelveticaNeue-Medium",
              "size": 20
            }
          },
          "paragraphStyle": {
            "_class": "paragraphStyle",
            "alignment": 0
          },
          "textStyleVerticalAlignmentKey": 0
        },
        "length": 27,
        "location": 0
      }
    ],
    "string": "3. Elegir tipo de servicio "
  },
  "automaticallyDrawOnUnderlyingPath": false,
  "booleanOperation": -1,
  "clippingMaskMode": 0,
  "do_objectID": "79B22BB4-4373-468A-956F-51F0D6591EBA",
  "dontSynchroniseWithSymbol": false,
  "exportOptions": {
    "_class": "exportOptions",
    "do_objectID": "3CE93E66-6709-4A11-9EB8-6D053F6096CB",
    "exportFormats": [
    ],
    "includedLayerIds": [
    ],
    "layerOptions": 0,
    "shouldTrim": false
  },
  "frame": {
    "_class": "rect",
    "constrainProportions": false,
    "do_objectID": "7D161083-546F-48BC-B4C1-942EF113FD0F",
    "height": 27,
    "width": 280,
    "x": 0,
    "y": 0
  },
  "glyphBounds": "{{0, 5}, {221, 20}}",
  "hasClippingMask": false,
  "isFixedToViewport": false,
  "isFlippedHorizontal": false,
  "isFlippedVertical": false,
  "isLocked": false,
  "isVisible": true,
  "layerListExpandedType": 0,
  "lineSpacingBehaviour": 2,
  "name": "3. Elegir tipo de se",
  "nameIsFixed": false,
  "resizingConstraint": 47,
  "resizingType": 0,
  "rotation": 0,
  "sharedStyleID": "20EC1026-ECF0-4628-9FB3-D14DB872EE30",
  "shouldBreakMaskChain": false,
  "style": {
    "_class": "style",
    "contextSettings": {
      "_class": "graphicsContextSettings",
      "blendMode": 0,
      "do_objectID": "76898D8E-CBDF-44F4-BD52-9754DE2FFBB5",
      "opacity": 0.87
    },
    "do_objectID": "0BE74E1E-2C53-4039-9341-FB495AD1573E",
    "endMarkerType": 0,
    "miterLimit": 10,
    "startMarkerType": 0,
    "textStyle": {
      "_class": "textStyle",
      "do_objectID": "33110040-C536-4D6C-B5F8-635CE83386B8",
      "encodedAttributes": {
        "MSAttributedStringColorAttribute": {
          "_class": "color",
          "alpha": 1,
          "blue": 0.1254901960784314,
          "green": 0.1254901960784314,
          "red": 0.1254901960784314
        },
        "MSAttributedStringFontAttribute": {
          "_class": "fontDescriptor",
          "attributes": {
            "name": "HelveticaNeue-Medium",
            "size": 20
          }
        },
        "paragraphStyle": {
          "_class": "paragraphStyle",
          "alignment": 0
        },
        "textStyleVerticalAlignmentKey": 0
      },
      "verticalAlignment": 0
    },
    "windingRule": 1
  },
  "textBehaviour": 2
}