{
  "_class": "group",
  "booleanOperation": -1,
  "clippingMaskMode": 0,
  "do_objectID": "AC2BA958-DFCC-4A60-A66E-829DE7DE6C7B",
  "exportOptions": {
    "_class": "exportOptions",
    "do_objectID": "43099331-240E-4FEB-A27F-9C603596CBB3",
    "exportFormats": [
    ],
    "includedLayerIds": [
    ],
    "layerOptions": 0,
    "shouldTrim": false
  },
  "frame": {
    "_class": "rect",
    "constrainProportions": false,
    "do_objectID": "50644186-3CAE-4BA7-985D-FAD096E5B748",
    "height": 19,
    "width": 278,
    "x": 0,
    "y": 0
  },
  "hasClickThrough": false,
  "hasClippingMask": false,
  "isFixedToViewport": false,
  "isFlippedHorizontal": false,
  "isFlippedVertical": false,
  "isLocked": false,
  "isVisible": true,
  "layerListExpandedType": 0,
  "layers": [
    {
      "class": "symbolInstance",
      "id": "54CE4590-8A8A-4055-A73E-7A11D5C1F5E9"
    },
    {
      "class": "text",
      "id": "C642EE0A-794B-4F6C-BC02-A657ED86F5A9"
    }
  ],
  "name": "Group 6",
  "nameIsFixed": false,
  "resizingConstraint": 63,
  "resizingType": 0,
  "rotation": 0,
  "shouldBreakMaskChain": false,
  "style": {
    "_class": "style",
    "do_objectID": "1D9A117B-B882-44A9-A0EA-73099E176CDA",
    "endMarkerType": 0,
    "miterLimit": 10,
    "startMarkerType": 0,
    "windingRule": 1
  }
}