{
  "_class": "bitmap",
  "booleanOperation": -1,
  "clippingMask": "{{0, 0}, {1, 1}}",
  "clippingMaskMode": 0,
  "do_objectID": "546FE0E7-5403-4E4E-A568-EFDB0650BF78",
  "exportOptions": {
    "_class": "exportOptions",
    "do_objectID": "6EB2126B-E285-4752-90F4-7ADE314EFC85",
    "exportFormats": [
    ],
    "includedLayerIds": [
    ],
    "layerOptions": 0,
    "shouldTrim": false
  },
  "fillReplacesImage": false,
  "frame": {
    "_class": "rect",
    "constrainProportions": true,
    "do_objectID": "C5B1CDED-569A-4869-8900-D4D688ABC9D2",
    "height": 648,
    "width": 722,
    "x": 0,
    "y": 0
  },
  "hasClippingMask": false,
  "image": {
    "_class": "MSJSONFileReference",
    "_ref": "images/44c3f198a383ac43c20b7f916870b71d00e6d8c6.png",
    "_ref_class": "MSImageData"
  },
  "intendedDPI": 144,
  "isFixedToViewport": false,
  "isFlippedHorizontal": false,
  "isFlippedVertical": false,
  "isLocked": false,
  "isVisible": true,
  "layerListExpandedType": 0,
  "name": "Captura de pantalla 2018-12-10 a la(s) 00.47.15",
  "nameIsFixed": false,
  "resizingConstraint": 63,
  "resizingType": 0,
  "rotation": 0,
  "shouldBreakMaskChain": false,
  "style": {
    "_class": "style",
    "do_objectID": "D44ECC31-0FD9-47CC-BDBE-E7A5281D4C3C",
    "endMarkerType": 0,
    "miterLimit": 10,
    "startMarkerType": 0,
    "windingRule": 1
  }
}