{
  "_class": "group",
  "booleanOperation": -1,
  "clippingMaskMode": 0,
  "do_objectID": "689C64B0-15A7-4AE2-8031-71EFAEE97E63",
  "exportOptions": {
    "_class": "exportOptions",
    "do_objectID": "0970F6A0-9408-4FC6-99B5-E79EEBBD0AED",
    "exportFormats": [
      {
        "_class": "exportFormat",
        "absoluteSize": 0,
        "fileFormat": "png",
        "name": "",
        "namingScheme": 0,
        "scale": 1,
        "visibleScaleType": 0
      }
    ],
    "includedLayerIds": [
    ],
    "layerOptions": 0,
    "shouldTrim": false
  },
  "frame": {
    "_class": "rect",
    "constrainProportions": false,
    "do_objectID": "067E2094-8E56-4019-8837-ECDFCE66124F",
    "height": 118,
    "width": 1440,
    "x": 0,
    "y": 0
  },
  "hasClickThrough": false,
  "hasClippingMask": false,
  "isFixedToViewport": false,
  "isFlippedHorizontal": false,
  "isFlippedVertical": false,
  "isLocked": false,
  "isVisible": true,
  "layerListExpandedType": 2,
  "layers": [
    {
      "class": "rectangle",
      "id": "513DC60A-7422-491D-97EE-5884DD626FEC"
    }
  ],
  "name": "Cabecera",
  "nameIsFixed": true,
  "resizingConstraint": 63,
  "resizingType": 0,
  "rotation": 0,
  "shouldBreakMaskChain": false,
  "style": {
    "_class": "style",
    "do_objectID": "C9AB1808-711C-46F5-93ED-52A0ABEEB529",
    "endMarkerType": 0,
    "miterLimit": 10,
    "shadows": [
      {
        "_class": "shadow",
        "blurRadius": 4,
        "color": {
          "_class": "color",
          "alpha": 0.5,
          "blue": 0.9254901960784314,
          "green": 0.9254901960784314,
          "red": 0.9254901960784314
        },
        "contextSettings": {
          "_class": "graphicsContextSettings",
          "blendMode": 0,
          "opacity": 1
        },
        "isEnabled": true,
        "offsetX": 0,
        "offsetY": 2,
        "spread": 0
      }
    ],
    "startMarkerType": 0,
    "windingRule": 1
  }
}